{"cameraMode":{"drawMode":0,"name":"Shaded","section":"Shading Mode"},"sceneLighting":true,"audioPlay":false,"sceneViewState":{"m_AlwaysRefresh":false,"showFog":false,"showSkybox":false,"showFlares":false,"showImageEffects":false,"showParticleSystems":false,"showVisualEffectGraphs":true,"m_FxEnabled":true},"in2DMode":false,"pivot":{"x":0.9729893207550049,"y":5.09531307220459,"z":-13.487274169921875},"rotation":{"x":0.14454597234725953,"y":-0.7989429235458374,"z":0.21237331628799439,"w":0.543784499168396},"size":0.9179849028587341,"orthographic":false}